{"EditorStatuses":[{"EditorSessionStatus":1,"ProcessId":7304,"Session":{"ApplicationName":"Editor.exe","Id":"296f8b92-41e0-11e8-82d3-1cb72cafadd6","ParentApplicationName":"","ParentId":"","ProjectId":"{8E55B5AA-95F4-4CEC-BA72-0FE78F1CB7D4}","StartTime":"2018-04-17T01:39:26.846Z","VersionId":"1.13.0.0"}},{"EditorSessionStatus":1,"ProcessId":12316,"Session":{"ApplicationName":"Editor.exe","Id":"6d256706-420b-11e8-82d3-1cb72cafadd6","ParentApplicationName":"","ParentId":"","ProjectId":"{8E55B5AA-95F4-4CEC-BA72-0FE78F1CB7D4}","StartTime":"2018-04-17T06:49:08.804Z","VersionId":"1.13.0.0"}},{"EditorSessionStatus":1,"ProcessId":14852,"Session":{"ApplicationName":"Editor.exe","Id":"70d907da-41e0-11e8-82d3-1cb72cafadd6","ParentApplicationName":"","ParentId":"","ProjectId":"{8E55B5AA-95F4-4CEC-BA72-0FE78F1CB7D4}","StartTime":"2018-04-17T01:41:26.655Z","VersionId":"1.13.0.0"}},{"EditorSessionStatus":1,"ProcessId":16504,"Session":{"ApplicationName":"Editor.exe","Id":"31500c57-428a-11e8-82d3-1cb72cafadd6","ParentApplicationName":"","ParentId":"","ProjectId":"{8E55B5AA-95F4-4CEC-BA72-0FE78F1CB7D4}","StartTime":"2018-04-17T21:56:34.505Z","VersionId":"1.13.0.0"}},{"EditorSessionStatus":1,"ProcessId":18952,"Session":{"ApplicationName":"Editor.exe","Id":"006b7649-428b-11e8-82d3-1cb72cafadd6","ParentApplicationName":"","ParentId":"","ProjectId":"{8E55B5AA-95F4-4CEC-BA72-0FE78F1CB7D4}","StartTime":"2018-04-17T22:02:21.973Z","VersionId":"1.13.0.0"}},{"EditorSessionStatus":1,"ProcessId":20808,"Session":{"ApplicationName":"Editor.exe","Id":"cbc241c2-41d8-11e8-82d3-1cb72cafadd6","ParentApplicationName":"","ParentId":"","ProjectId":"{8E55B5AA-95F4-4CEC-BA72-0FE78F1CB7D4}","StartTime":"2018-04-17T00:46:43.205Z","VersionId":"1.13.0.0"}}]}
